kafka_tfrx/__init__.py
kafka_tfrx/observer.py
kafka_tfrx/stream.py
kafka_tfrx-0.12.dist-info/METADATA
kafka_tfrx-0.12.dist-info/RECORD
kafka_tfrx-0.12.dist-info/WHEEL
kafka_tfrx-0.12.dist-info/entry_points.txt
kafka_tfrx-0.12.dist-info/top_level.txt
