Metadata-Version: 2.1
Name: kafka-tfrx
Version: 0.12
Summary: Add a short description here!
Home-page: http://...
Author: Carlo Mazzaferro
Author-email: carlo.mazzaferro@gmail.com
License: mit
Platform: any
Classifier: Development Status :: 4 - Beta
Classifier: Programming Language :: Python
